img_processing_dio/__init__.py
img_processing_dio/processing/__init__.py
img_processing_dio/processing/combination.py
img_processing_dio/processing/transformation.py
img_processing_dio/utils/__init__.py
img_processing_dio/utils/io.py
img_processing_dio/utils/plot.py.py
img_processing_dio-0.0.1.dist-info/METADATA
img_processing_dio-0.0.1.dist-info/WHEEL
img_processing_dio-0.0.1.dist-info/top_level.txt
img_processing_dio-0.0.1.dist-info/RECORD
